napari_wsireg/__init__.py
napari_wsireg/_version.py
napari_wsireg/_widget.py
napari_wsireg/napari.yaml
napari_wsireg/_tests/__init__.py
napari_wsireg/_tests/test_wsireg_2d_main.py
napari_wsireg/_tests/fixtures/__init__.py
napari_wsireg/_tests/fixtures/im_fixtures.py
napari_wsireg/_tests/fixtures/mc_im_8bit.tiff
napari_wsireg/_tests/fixtures/mini_czi.czi
napari_wsireg/_tests/fixtures/mini_czi_mc.czi
napari_wsireg/_tests/fixtures/rgb_im_8bit.tiff
napari_wsireg/_tests/fixtures/sc_im_8bit.tiff
napari_wsireg/_tests/fixtures/test-anno-data.geojson
napari_wsireg/data/__init__.py
napari_wsireg/data/czi_image.py
napari_wsireg/data/tifffile_image.py
napari_wsireg/data/wsireg_image.py
napari_wsireg/data/_tests/__init__.py
napari_wsireg/data/_tests/test_czi_image.py
napari_wsireg/data/_tests/test_tifffile_image.py
napari_wsireg/data/utils/__init__.py
napari_wsireg/data/utils/czi.py
napari_wsireg/data/utils/graph.py
napari_wsireg/data/utils/image.py
napari_wsireg/data/utils/shapes.py
napari_wsireg/data/utils/tifffile_meta.py
napari_wsireg/data/utils/transform.py
napari_wsireg/gui/__init__.py
napari_wsireg/gui/queue.py
napari_wsireg/gui/setup_gui.py
napari_wsireg/gui/dialogs/__init__.py
napari_wsireg/gui/dialogs/add_merge.py
napari_wsireg/gui/dialogs/add_modality.py
napari_wsireg/gui/dialogs/_tests/__init__.py
napari_wsireg/gui/dialogs/_tests/test_gui_dialogs.py
napari_wsireg/gui/queue/__init__.py
napari_wsireg/gui/queue/queue.py
napari_wsireg/gui/resources/wsireg-logo-light.svg
napari_wsireg/gui/resources/wsireg-logo.svg
napari_wsireg/gui/setup_sub/__init__.py
napari_wsireg/gui/setup_sub/graph.py
napari_wsireg/gui/setup_sub/modality.py
napari_wsireg/gui/setup_sub/paths.py
napari_wsireg/gui/setup_sub/preprocessing.py
napari_wsireg/gui/setup_sub/project.py
napari_wsireg/gui/utils/__init__.py
napari_wsireg/gui/utils/colors.py
napari_wsireg/gui/utils/file.py
napari_wsireg-0.1.2.dist-info/LICENSE
napari_wsireg-0.1.2.dist-info/METADATA
napari_wsireg-0.1.2.dist-info/WHEEL
napari_wsireg-0.1.2.dist-info/entry_points.txt
napari_wsireg-0.1.2.dist-info/top_level.txt
napari_wsireg-0.1.2.dist-info/RECORD
