Metadata-Version: 2.1
Name: napari-wsireg
Version: 0.1.2
Summary: plugin to perform whole slide image registration with wsireg
Home-page: https://github.com/nhpatterson/napari-wsireg
Author: Nathan Heath Patterson
Author-email: heath.patterson@vanderbilt.edu
License: BSD-3-Clause
Project-URL: Bug Tracker, https://github.com/nhpatterson/napari-wsireg/issues
Project-URL: Documentation, https://github.com/nhpatterson/napari-wsireg#README.md
Project-URL: Source Code, https://github.com/nhpatterson/napari-wsireg
Project-URL: User Support, https://github.com/nhpatterson/napari-wsireg/issues
Classifier: Development Status :: 4 - Beta
Classifier: Framework :: napari
Classifier: Intended Audience :: Developers
Classifier: License :: OSI Approved :: BSD License
Classifier: Operating System :: OS Independent
Classifier: Programming Language :: Python
Classifier: Programming Language :: Python :: 3
Classifier: Programming Language :: Python :: 3 :: Only
Classifier: Programming Language :: Python :: 3.8
Classifier: Programming Language :: Python :: 3.9
Classifier: Topic :: Software Development :: Testing
Requires-Python: >=3.8
License-File: LICENSE
Requires-Dist: wsireg (>=0.3.6)
Requires-Dist: SimpleITK
Requires-Dist: czifile
Requires-Dist: dask
Requires-Dist: imagecodecs
Requires-Dist: napari
Requires-Dist: numpy
Requires-Dist: ome-types
Requires-Dist: pint
Requires-Dist: qtpy
Requires-Dist: tifffile
Requires-Dist: zarr (>=2.10.3)
Requires-Dist: napari-geojson
Requires-Dist: networkx
Requires-Dist: matplotlib
